basic_colormath/__init__.py
basic_colormath/conversion.py
basic_colormath/distance.py
basic_colormath/mix.py
basic_colormath/py.typed
basic_colormath/type_hints.py
basic_colormath2-0.1.1.dist-info/METADATA
basic_colormath2-0.1.1.dist-info/WHEEL
basic_colormath2-0.1.1.dist-info/top_level.txt
basic_colormath2-0.1.1.dist-info/RECORD
