Metadata-Version: 2.1
Name: basic_colormath2
Version: 0.1.1
Summary: Simple color conversion and perceptual (DeltaE CIE 2000) difference
Author-email: Shay Hill <shay_public@hotmail.com>
License: MIT
Requires-Python: >=3.8
Provides-Extra: dev
Requires-Dist: commitizen ; extra == 'dev'
Requires-Dist: colormath ; extra == 'dev'
Requires-Dist: numpy ; extra == 'dev'
Requires-Dist: pre-commit ; extra == 'dev'
Requires-Dist: pytest ; extra == 'dev'
Requires-Dist: tox ; extra == 'dev'
